async_gaussdb/_asyncio_compat.py
async_gaussdb/cursor.py
async_gaussdb/_version.py
async_gaussdb/utils.py
async_gaussdb/compat.py
async_gaussdb/connection.py
async_gaussdb/introspection.py
async_gaussdb/serverversion.py
async_gaussdb/cluster.py
async_gaussdb/connresource.py
async_gaussdb/pool.py
async_gaussdb/types.py
async_gaussdb/__init__.py
async_gaussdb/transaction.py
async_gaussdb/connect_utils.py
async_gaussdb/prepared_stmt.py
async_gaussdb/pgproto/cpythonx.pxd
async_gaussdb/pgproto/pgproto.cpython-38-x86_64-linux-gnu.so
async_gaussdb/pgproto/buffer.pxd
async_gaussdb/pgproto/__init__.pxd
async_gaussdb/pgproto/pgproto.pyx
async_gaussdb/pgproto/pgproto.pyi
async_gaussdb/pgproto/frb.pyx
async_gaussdb/pgproto/buffer.pyx
async_gaussdb/pgproto/hton.pxd
async_gaussdb/pgproto/pgproto.pxd
async_gaussdb/pgproto/uuid.pyx
async_gaussdb/pgproto/consts.pxi
async_gaussdb/pgproto/debug.pxd
async_gaussdb/pgproto/frb.pxd
async_gaussdb/pgproto/tohex.pxd
async_gaussdb/pgproto/types.py
async_gaussdb/pgproto/__init__.py
async_gaussdb/pgproto/codecs/datetime.pyx
async_gaussdb/pgproto/codecs/hstore.pyx
async_gaussdb/pgproto/codecs/__init__.pxd
async_gaussdb/pgproto/codecs/context.pyx
async_gaussdb/pgproto/codecs/network.pyx
async_gaussdb/pgproto/codecs/misc.pyx
async_gaussdb/pgproto/codecs/text.pyx
async_gaussdb/pgproto/codecs/pg_snapshot.pyx
async_gaussdb/pgproto/codecs/json.pyx
async_gaussdb/pgproto/codecs/int.pyx
async_gaussdb/pgproto/codecs/uuid.pyx
async_gaussdb/pgproto/codecs/bytea.pyx
async_gaussdb/pgproto/codecs/numeric.pyx
async_gaussdb/pgproto/codecs/geometry.pyx
async_gaussdb/pgproto/codecs/jsonpath.pyx
async_gaussdb/pgproto/codecs/float.pyx
async_gaussdb/pgproto/codecs/tid.pyx
async_gaussdb/pgproto/codecs/bits.pyx
async_gaussdb/_testbase/fuzzer.py
async_gaussdb/_testbase/__init__.py
async_gaussdb/protocol/cpythonx.pxd
async_gaussdb/protocol/scram.pyx
async_gaussdb/protocol/sha256.pxd
async_gaussdb-0.30.0.dist-info/RECORD
async_gaussdb-0.30.0.dist-info/AUTHORS
async_gaussdb-0.30.0.dist-info/LICENSE
async_gaussdb-0.30.0.dist-info/METADATA
async_gaussdb-0.30.0.dist-info/top_level.txt
async_gaussdb-0.30.0.dist-info/WHEEL
