Metadata-Version: 2.1
Name: async_gaussdb
Version: 0.30.0
Summary: An asyncio GaussDB driver
License: Apache-2.0
Project-URL: github, https://github.com/MagicStack/async_gaussdb
Keywords: database,gaussdb
Classifier: Development Status :: 5 - Production/Stable
Classifier: Framework :: AsyncIO
Classifier: Intended Audience :: Developers
Classifier: License :: OSI Approved :: Apache Software License
Classifier: Operating System :: POSIX
Classifier: Operating System :: MacOS :: MacOS X
Classifier: Operating System :: Microsoft :: Windows
Classifier: Programming Language :: Python :: 3 :: Only
Classifier: Programming Language :: Python :: 3.8
Classifier: Programming Language :: Python :: 3.9
Classifier: Programming Language :: Python :: 3.10
Classifier: Programming Language :: Python :: 3.11
Classifier: Programming Language :: Python :: 3.12
Classifier: Programming Language :: Python :: Implementation :: CPython
Classifier: Topic :: Database :: Front-Ends
Requires-Python: >=3.8.0
License-File: LICENSE
License-File: AUTHORS
Requires-Dist: async-timeout>=4.0.3; python_version < "3.11.0"
Provides-Extra: docs
Requires-Dist: Sphinx~=8.1.3; extra == "docs"
Requires-Dist: sphinx-rtd-theme>=1.2.2; extra == "docs"
Provides-Extra: gssauth
Requires-Dist: gssapi; platform_system != "Windows" and extra == "gssauth"
Requires-Dist: sspilib; platform_system == "Windows" and extra == "gssauth"
